Collections/Node.py
Collections/Queue.py
Collections/Stack.py
Collections/__init__.py
Collections/Lists/ArrayList.py
Collections/Lists/LinkedList.py
Collections/Lists/__init__.py
collections_example-1.1.dist-info/LICENSE.txt
collections_example-1.1.dist-info/METADATA
collections_example-1.1.dist-info/WHEEL
collections_example-1.1.dist-info/top_level.txt
collections_example-1.1.dist-info/RECORD
